{
  "footerSocialLinks": {
    "items": [{
      "altText": "Follow us on Facebook",
      "href": "https://www.facebook.com/massgov",
      "icon": "@atoms/05-icons/svg-facebook.twig"
    },{
      "altText": "Follow us on Twitter",
      "href": "https://twitter.com/massgov",
      "icon": "@atoms/05-icons/svg-twitter.twig"
    },{
      "altText": "Follow us on LinkedIn",
      "href": "https://www.linkedin.com/company/commonwealth-of-massachusetts",
      "icon": "@atoms/05-icons/svg-linkedin.twig"
    },{
      "altText": "Follow us on Youtube",
      "href": "https://www.youtube.com/user/massgov",
      "icon": "@atoms/05-icons/svg-youtube.twig"
    },{
      "altText": "Follow us on Instagram",
      "href": "https://www.instagram.com/massgov/",
      "icon": "@atoms/05-icons/svg-instagram.twig"
    }]
  }
}
